ows_language_model/VERSION
ows_language_model/__init__.py
ows_language_model/model.py
ows_language_model/pipeline.py
ows_language_model/predict.py
ows_language_model/train_pipeline.py
ows_language_model/config/__init__.py
ows_language_model/config/config.py
ows_language_model/datasets/__init__.py
ows_language_model/datasets/test_data/__init__.py
ows_language_model/processing/__init__.py
ows_language_model/processing/data_management.py
ows_language_model/processing/errors.py
ows_language_model/processing/preprocessors.py
ows_language_model/processing/scraping.py
ows_language_model/trained_models/__init__.py
ows_language_model-0.2.0.dist-info/METADATA
ows_language_model-0.2.0.dist-info/WHEEL
ows_language_model-0.2.0.dist-info/top_level.txt
ows_language_model-0.2.0.dist-info/RECORD
